{
    "display": {
        "icon": {
            "item": "minecraft:player_head",
            "nbt": "{SkullOwner:\"potage00\"}"
        },
        "title": {
            "text": "首狩りぽたーじゅ"
        },
        "description": {
            "text": "ぽたーじゅの頭を手に入れろ！"
        },
        "frame": "task",
        "show_toast": false,
        "announce_to_chat": false,
        "hidden": false,
        "background": "minecraft:textures/block/magma.png"
    },
    "criteria": {
        "potage_head": {
            "trigger": "minecraft:inventory_changed",
            "conditions": {
                "items": [
                    {
                        "item": "minecraft:player_head",
                        "nbt": "{SkullOwner:\"potage00\"}"
                    }
                ]
            }
        }
    },
    "requirements": [
        ["potage_head"]
    ]
}